sdk_utils/__init__.py
sdk_utils/baidu_cloud.py
sdk_utils/baidu_cloud_bypy.py
tests/__init__.py
tests/test_baidu_cloud.py
sdk_utils-0.1.2.dist-info/METADATA
sdk_utils-0.1.2.dist-info/WHEEL
sdk_utils-0.1.2.dist-info/top_level.txt
sdk_utils-0.1.2.dist-info/RECORD
