Metadata-Version: 2.1
Name: sdk_utils
Version: 0.1.2
Summary: 一个集成SDK的工具库，如百度云盘API
Home-page: https://github.com/guyue55/sdk_utils
Author: Guyue
Author-email: guyuecw@qq.com
License: MIT
Keywords: baidu,cloud,sdk,api,client
Classifier: Programming Language :: Python :: 3
Classifier: License :: OSI Approved :: MIT License
Classifier: Operating System :: OS Independent
Classifier: Development Status :: 4 - Beta
Classifier: Intended Audience :: Developers
Classifier: Topic :: Software Development :: Libraries :: Python Modules
Classifier: Topic :: Internet :: WWW/HTTP
Requires-Python: >=3.6
Requires-Dist: requests>=2.25.0
Requires-Dist: bypy>=1.7.0
Requires-Dist: tqdm>=4.50.0
